dexweb/__init__.py
dexweb/dexgen.py
dexweb/dexweb.py
dexweb/favicon.ico
dexweb/styles.css
dexweb-4.1.6.dist-info/METADATA
dexweb-4.1.6.dist-info/WHEEL
dexweb-4.1.6.dist-info/licenses/LICENSE
dexweb-4.1.6.dist-info/RECORD
