Metadata-Version: 2.4
Name: dexweb
Version: 4.1.6
Summary: Dexweb makes dex, a programmatically generated website, to put on the web
Project-URL: Homepage, https://alinoorul.github.io/researchengine
Project-URL: Issues, https://github.com/matrixdex/devpy
Project-URL: Documentation, https://matrixdex.github.io/dexweb
Project-URL: Repository, https://github.com/matrixdex/devpy/tree/dexweb
Author-email: Noorul Ali <manonthemoon13131@gmail.com>
License-File: LICENSE
Classifier: License :: CC0 1.0 Universal (CC0 1.0) Public Domain Dedication
Classifier: Operating System :: OS Independent
Classifier: Programming Language :: Python :: 3
Requires-Python: >=3.8
Requires-Dist: beautifulsoup4
Requires-Dist: importlib-resources
Requires-Dist: mammoth
Requires-Dist: pypdf
